indico_citadel/__init__.py
indico_citadel/backend.py
indico_citadel/cli.py
indico_citadel/plugin.py
indico_citadel/result_schemas.py
indico_citadel/schemas.py
indico_citadel/search.py
indico_citadel/util.py
indico_citadel/migrations/20210330_1742_0cf18be7ade1_add_mapping_table.py
indico_citadel/models/__init__.py
indico_citadel/models/id_map.py
indico_citadel/templates/event_category_warning.html
indico_citadel/translations/messages.pot
indico_citadel/translations/cs_CZ/LC_MESSAGES/messages.mo
indico_citadel/translations/cs_CZ/LC_MESSAGES/messages.po
indico_citadel/translations/de_DE/LC_MESSAGES/messages.mo
indico_citadel/translations/de_DE/LC_MESSAGES/messages.po
indico_citadel/translations/en_CA/LC_MESSAGES/messages.mo
indico_citadel/translations/en_CA/LC_MESSAGES/messages.po
indico_citadel/translations/en_GB/LC_MESSAGES/messages.mo
indico_citadel/translations/en_GB/LC_MESSAGES/messages.po
indico_citadel/translations/es_ES/LC_MESSAGES/messages.mo
indico_citadel/translations/es_ES/LC_MESSAGES/messages.po
indico_citadel/translations/fr_FR/LC_MESSAGES/messages.mo
indico_citadel/translations/fr_FR/LC_MESSAGES/messages.po
indico_citadel/translations/hu_HU/LC_MESSAGES/messages.mo
indico_citadel/translations/hu_HU/LC_MESSAGES/messages.po
indico_citadel/translations/it_IT/LC_MESSAGES/messages.mo
indico_citadel/translations/it_IT/LC_MESSAGES/messages.po
indico_citadel/translations/ja_JP/LC_MESSAGES/messages.mo
indico_citadel/translations/ja_JP/LC_MESSAGES/messages.po
indico_citadel/translations/mn_MN/LC_MESSAGES/messages.mo
indico_citadel/translations/mn_MN/LC_MESSAGES/messages.po
indico_citadel/translations/pl_PL/LC_MESSAGES/messages.mo
indico_citadel/translations/pl_PL/LC_MESSAGES/messages.po
indico_citadel/translations/pt_BR/LC_MESSAGES/messages.mo
indico_citadel/translations/pt_BR/LC_MESSAGES/messages.po
indico_citadel/translations/sv_SE/LC_MESSAGES/messages.mo
indico_citadel/translations/sv_SE/LC_MESSAGES/messages.po
indico_plugin_citadel-3.3.3.dist-info/METADATA
indico_plugin_citadel-3.3.3.dist-info/WHEEL
indico_plugin_citadel-3.3.3.dist-info/entry_points.txt
indico_plugin_citadel-3.3.3.dist-info/RECORD
