Metadata-Version: 2.4
Name: indico-plugin-citadel
Version: 3.3.3
Summary: Indico search+livesync backend using Citadel+ElasticSearch
Project-URL: GitHub, https://github.com/indico/indico-plugins
Author-email: Indico Team <indico-team@cern.ch>
License-Expression: MIT
Classifier: Environment :: Plugins
Classifier: Environment :: Web Environment
Classifier: License :: OSI Approved :: MIT License
Classifier: Programming Language :: Python :: 3.12
Requires-Python: <3.13,>=3.12.2
Requires-Dist: indico-plugin-livesync>=3.3.dev0
Requires-Dist: indico>=3.3.7.dev0
